{
  "source": "CBC News",
  "generated_at": "2026-01-02T09:15:38.736743-05:00",
  "timezone": "America/Toronto",
  "items": [
    {
      "id": "f3553a965dc8b73a0b4afecb2eca321a739b24d5",
      "url": "https://www.cbc.ca/sports/olympics/winter/hockey/blayre-turnbull-olympic-feature-2026-9.7030655?cmp=rss",
      "title": "Something to prove: How Blayre Turnbull became the ‘glue’ of the Canadian women’s hockey team",
      "published_at": "2026-01-02T04:00:00-05:00",
      "section": "Top Stories",
      "summary_auto": "Blayre Turnbull, the captain of the Toronto Sceptres is looking to compete in her third Olympics in February. She owns an Olympic gold medal from 2022 and three world championships. Yet for all her success, the 32-year-old always feels like she has something to prove.",
      "bias_heuristic": {
        "article_type": "News",
        "sentiment": 0.91,
        "subjectivity_hint": "low"
      }
    },
    {
      "id": "460ac1ffdd2b324e0657a46ded12e8682b98c94e",
      "url": "https://www.cbc.ca/news/canada/edmonton/alberta-december-snow-9.7031817?cmp=rss",
      "title": "Parts of Alberta just saw some of the most snow they've ever seen in the month of December",
      "published_at": "2026-01-02T03:00:00-05:00",
      "section": "Top Stories",
      "summary_auto": "As of Dec 28, communities including Grande Prairie, Banff and Fort McMurray had seen one of their wettest Decembers on record.",
      "bias_heuristic": {
        "article_type": "News",
        "sentiment": 0.0,
        "subjectivity_hint": "low"
      }
    },
    {
      "id": "d0fcdc97446db06bdfe68be1d36e304128cab77e",
      "url": "https://www.cbc.ca/news/world/north-korea-heir-kim-jong-un-9.7032155?cmp=rss",
      "title": "Kim Jong-un's daughter visits family mausoleum, promoting her potential status as heir in North Korea",
      "published_at": "2026-01-02T01:48:12-05:00",
      "section": "Top Stories",
      "summary_auto": "The teenage daughter of North Korean leader Kim Jong-un made her first known visit to a sacred family mausoleum, a step that experts say bolstered her status as her father's potential heir.",
      "bias_heuristic": {
        "article_type": "News",
        "sentiment": 0.361,
        "subjectivity_hint": "low"
      }
    },
    {
      "id": "f73bdce750a09316d2ab1399beab06494aa8f9e0",
      "url": "https://www.cbc.ca/news/world/trump-iran-protests-9.7032152?cmp=rss",
      "title": "Trump, top Iranian officials exchange threats over protests in Iran",
      "published_at": "2026-01-02T01:37:41-05:00",
      "section": "Top Stories",
      "summary_auto": "U.S. President Donald Trump and top Iranian officials exchanged duelling threats on Friday as widening economic protests swept across parts of the Islamic Republic, further escalating tensions between the countries.",
      "bias_heuristic": {
        "article_type": "News",
        "sentiment": -0.818,
        "subjectivity_hint": "low"
      }
    },
    {
      "id": "f73bdce750a09316d2ab1399beab06494aa8f9e0",
      "url": "https://www.cbc.ca/news/world/trump-iran-protests-9.7032152?cmp=rss",
      "title": "Trump and top Iranian officials exchange threats over protests roiling Iran",
      "published_at": "2026-01-02T01:37:41-05:00",
      "section": "World",
      "summary_auto": "U.S. President Donald Trump and top Iranian officials exchanged duelling threats on Friday as widening economic protests swept across parts of the Islamic Republic, further escalating tensions between the countries.",
      "bias_heuristic": {
        "article_type": "News",
        "sentiment": -0.818,
        "subjectivity_hint": "low"
      }
    },
    {
      "id": "730665fc86f0fd4433ebaf5bc155f28fc10521f6",
      "url": "https://www.cbc.ca/news/world/swiss-fire-bar-9.7032125?cmp=rss",
      "title": "Swiss face painful task of identifying victims of deadly bar fire",
      "published_at": "2026-01-02T01:13:20-05:00",
      "section": "World",
      "summary_auto": "Investigators on Friday set about the painful task of identifying the burned bodies of a blaze that engulfed a crowded bar and killed around 40 people at a New Year's Eve party in the upscale Swiss ski resort of Crans-Montana.",
      "bias_heuristic": {
        "article_type": "News",
        "sentiment": -0.906,
        "subjectivity_hint": "low"
      }
    },
    {
      "id": "724d81c7524837ccc62ffe068d7cdf9235cbc541",
      "url": "https://www.cbc.ca/news/politics/parliamentary-budget-officer-economists-peer-review-9.7006741?cmp=rss",
      "title": "Leading economists want less talk, more numbers from federal budget watchdog",
      "published_at": "2026-01-01T23:01:26-05:00",
      "section": "Top Stories",
      "summary_auto": "",
      "bias_heuristic": {
        "article_type": "News",
        "sentiment": 0.077,
        "subjectivity_hint": "low"
      }
    },
    {
      "id": "7fbde9793905e060729eab924d30ca352b5f7067",
      "url": "https://www.cbc.ca/news/canada/first-person-zahra-khozema-working-out-9.7029372?cmp=rss",
      "title": "I spent over a decade obsessed with the gym. I’ve finally let myself stop",
      "published_at": "2026-01-01T23:00:00-05:00",
      "section": "Top Stories",
      "summary_auto": "When Zahra Khozema first started going to the gym in university, it made her feel powerful and beautiful. The guilt and stress came later.",
      "bias_heuristic": {
        "article_type": "News",
        "sentiment": -0.026,
        "subjectivity_hint": "medium"
      }
    },
    {
      "id": "16159d12d37a3a623467a9c4d5f529ce36ccc00c",
      "url": "https://www.cbc.ca/news/canada/montreal/quebecers-skydiving-world-record-florida-9.7021667?cmp=rss",
      "title": "Quebec City skydivers help set new world record for largest parachute formation",
      "published_at": "2026-01-01T23:00:00-05:00",
      "section": "Top Stories",
      "summary_auto": "Roughly 100 people from around the world, including some Quebecers, travelled to Lake Whales, Fla., in November to break the world record for largest parachute formation.",
      "bias_heuristic": {
        "article_type": "News",
        "sentiment": 0.402,
        "subjectivity_hint": "low"
      }
    },
    {
      "id": "51775ce0607027b447486b72b953f8cf153b4d83",
      "url": "https://www.cbc.ca/news/canada/manitoba/pimicikamak-cree-nation-power-outage-repairs-9.7032031?cmp=rss",
      "title": "Manitoba Hydro fixes downed line, ending Pimicikamak Cree Nation's frigid days in the dark",
      "published_at": "2026-01-01T11:29:50-05:00",
      "section": "Top Stories",
      "summary_auto": "Power is being restored to Pimicikamak Cree Nation nearly four days after a widespread power outage left community members without heat in freezing winter temperatures and promoted a state of emergency.",
      "bias_heuristic": {
        "article_type": "News",
        "sentiment": 0.44,
        "subjectivity_hint": "low"
      }
    },
    {
      "id": "51775ce0607027b447486b72b953f8cf153b4d83",
      "url": "https://www.cbc.ca/news/canada/manitoba/pimicikamak-cree-nation-power-outage-repairs-9.7032031?cmp=rss",
      "title": "Pimicikamak Cree Nation residents rejoice as power returns after Manitoba Hydro fixes downed line",
      "published_at": "2026-01-01T11:29:50-05:00",
      "section": "Canada",
      "summary_auto": "Power is being restored to Pimicikamak Cree Nation nearly four days after a widespread power outage left community members without heat in freezing winter temperatures and promoted a state of emergency.",
      "bias_heuristic": {
        "article_type": "News",
        "sentiment": 0.7,
        "subjectivity_hint": "low"
      }
    },
    {
      "id": "bf9690a93b303ec8e165341279b9e76f21f795e7",
      "url": "https://www.cbc.ca/sports/olympics/winter/ski-jumping/ski-jumper-abi-strate-1st-career-world-cup-gold-9.7032015?cmp=rss",
      "title": "Canadian ski jumper Abi Strate captures 1st career World Cup gold",
      "published_at": "2026-01-01T10:50:01-05:00",
      "section": "Top Stories",
      "summary_auto": "Canadian ski jumper Abi Strate started the new year with a bang by soaring to her first career World Cup victory on Thursday.",
      "bias_heuristic": {
        "article_type": "News",
        "sentiment": 0.0,
        "subjectivity_hint": "low"
      }
    },
    {
      "id": "15a24065f12a1b68e24a5173183ec0218040db54",
      "url": "https://www.cbc.ca/news/canada/calgary/no-drop-in-calgarians-water-usage-despite-request-from-city-after-water-main-break-9.7031950?cmp=rss",
      "title": "No drop in Calgarians' water usage despite request from city after water main break",
      "published_at": "2026-01-01T09:30:45-05:00",
      "section": "Top Stories",
      "summary_auto": "A day after officials first asked Calgarians to reduce their water use in the wake of Tuesday’s catastrophic water main break, the city says it is not seeing any real reduction in usage.",
      "bias_heuristic": {
        "article_type": "News",
        "sentiment": -0.337,
        "subjectivity_hint": "low"
      }
    }
  ]
}