{
  "source": "CBC News",
  "generated_at": "2026-03-24T14:54:38.918374-04:00",
  "timezone": "America/Toronto",
  "items": [
    {
      "id": "4f09efaabd65202ef446f738bb00795f69611dbe",
      "url": "https://www.cbc.ca/news/world/israel-army-lebanon-south-9.7140329?cmp=rss",
      "title": "Israel's defence minister says military plans occupy swathe of southern Lebanon",
      "published_at": "2026-03-24T10:46:23-04:00",
      "section": "Top Stories",
      "summary_auto": "Israel will occupy southern Lebanon up to the Litani River to create a \"defensive buffer,\" Defence Minister Israel Katz said on Tuesday, spelling out for the first time Israel's intent to seize territory amounting to nearly a tenth of Lebanon.",
      "bias_heuristic": {
        "article_type": "News",
        "sentiment": 0.459,
        "subjectivity_hint": "low"
      }
    },
    {
      "id": "d6141268ca7f09d2ef8461649f7b0f5ac52347d4",
      "url": "https://www.cbc.ca/news/politics/fraser-ford-smith-moe-ford-legault-judges-9.7140166?cmp=rss",
      "title": "Justice minister won't meet premiers' demand for 'sea change' to how judges are appointed",
      "published_at": "2026-03-24T09:04:09-04:00",
      "section": "Top Stories",
      "summary_auto": "Justice Minister Sean Fraser says he has no plans to change how judges are appointed in Canada after four premiers wrote to Prime Minister Mark Carney asking for more of a say in the process.",
      "bias_heuristic": {
        "article_type": "News",
        "sentiment": 0.716,
        "subjectivity_hint": "low"
      }
    },
    {
      "id": "e1e695dead6f64662d146a56038b045ebdc50d63",
      "url": "https://www.cbc.ca/news/science/nasa-lunar-gateway-9.7140073?cmp=rss",
      "title": "NASA plans $20B moon base, but pauses lunar space station project",
      "published_at": "2026-03-24T08:27:27-04:00",
      "section": "World",
      "summary_auto": "NASA is pausing plans to deploy a space station in lunar orbit and will instead use its components to construct ‌a $20 billion base on the moon's surface over the next seven years, its new chief Jared Isaacman said on Tuesday.",
      "bias_heuristic": {
        "article_type": "News",
        "sentiment": 0.0,
        "subjectivity_hint": "low"
      }
    },
    {
      "id": "ed33e08eb93cb26b6c74355aeae355b9681a748e",
      "url": "https://www.cbc.ca/news/canada/calgary/rcmp-probe-corruption-allegations-at-calgary-city-hall-warrants-executed-on-current-former-councillors-9.7140099?cmp=rss",
      "title": "RCMP probe corruption allegations at Calgary city hall; warrants executed on current, former councillors",
      "published_at": "2026-03-24T08:05:52-04:00",
      "section": "Canada",
      "summary_auto": "An RCMP-led corruption investigation is underway and at least one current and one former Calgary city councillor, as well as a business were subject to search warrants executed last week, CBC News has learned.",
      "bias_heuristic": {
        "article_type": "News",
        "sentiment": 0.273,
        "subjectivity_hint": "low"
      }
    },
    {
      "id": "22996d73eb6e750c9f98d60e5c7f5be471e8aeaf",
      "url": "https://www.cbc.ca/news/canada/hamilton/hamilton-harbour-sewage-leak-600k-fine-9.7140012?cmp=rss",
      "title": "City of Hamilton fined $600K for 26-year sewage leak into Hamilton Harbour",
      "published_at": "2026-03-24T08:05:28-04:00",
      "section": "Canada",
      "summary_auto": "The City of Hamilton says it remains committed to improving wastewater and stormwater systems after being slapped with a $600,000 fine for sewage leaking into the Hamilton Harbour for 26 years.",
      "bias_heuristic": {
        "article_type": "News",
        "sentiment": 0.511,
        "subjectivity_hint": "low"
      }
    },
    {
      "id": "978b42c3dedf4d018ac9902cd26b7126049b4223",
      "url": "https://www.cbc.ca/news/canada/edmonton/singh-highway-homicide-arrest-9.7139958?cmp=rss",
      "title": "18-year-old man charged with 2nd-degree murder in Alberta highway shooting",
      "published_at": "2026-03-24T07:44:10-04:00",
      "section": "Top Stories",
      "summary_auto": "An 18-year-old man has been charged with second-degree murder in a deadly daytime shooting on a highway south of Edmonton.",
      "bias_heuristic": {
        "article_type": "News",
        "sentiment": -0.919,
        "subjectivity_hint": "low"
      }
    },
    {
      "id": "66cb5deba6c70c7316b3c91e5909536c83e89f95",
      "url": "https://www.cbc.ca/news/canada/manitoba/manitoba-pst-groceries-2026-budget-9.7140023?cmp=rss",
      "title": "Manitoba to cut PST at grocery stores in new budget: premier",
      "published_at": "2026-03-24T07:41:49-04:00",
      "section": "Top Stories",
      "summary_auto": "Provincial taxes will be taken off more grocery store items under Manitoba's next budget, Premier Wab Kinew says.",
      "bias_heuristic": {
        "article_type": "News",
        "sentiment": -0.273,
        "subjectivity_hint": "low"
      }
    },
    {
      "id": "70a62f52ce22949a823410aea2c5b2e4cec35b23",
      "url": "https://www.cbc.ca/news/politics/long-ballot-protest-mp-committee-9.7140005?cmp=rss",
      "title": "To stop long ballot protests, MP committee calls on government to change candidacy rules",
      "published_at": "2026-03-24T07:28:13-04:00",
      "section": "Top Stories",
      "summary_auto": "A House of Commons committee is calling on the government to make changes to federal election rules it says would make it harder for electoral reform advocates to stage long ballot protests.",
      "bias_heuristic": {
        "article_type": "News",
        "sentiment": -0.612,
        "subjectivity_hint": "medium"
      }
    },
    {
      "id": "01a838752dbe8be2b8d027551b8b3db158eca763",
      "url": "https://www.cbc.ca/news/politics/federal-minimum-wage-increase-9.7140017?cmp=rss",
      "title": "Federal minimum wage increasing to $18.15 per hour",
      "published_at": "2026-03-24T07:27:09-04:00",
      "section": "Top Stories",
      "summary_auto": "The federal minimum wage will rise by 40 cents next week, a scheduled increase that keeps the wage in line with inflation.",
      "bias_heuristic": {
        "article_type": "News",
        "sentiment": 0.318,
        "subjectivity_hint": "low"
      }
    },
    {
      "id": "9d001b307761771364fecfe754e794abb6626c1b",
      "url": "https://www.cbc.ca/sports/future-of-sport-canada-commission-report-march-24-9.7139878?cmp=rss",
      "title": "'Fragmented, inconsistent, unsafe': Commission calls for sweeping change to sport in Canada",
      "published_at": "2026-03-24T07:03:20-04:00",
      "section": "Top Stories",
      "summary_auto": "A commission studying the future of sport in Canada has called for sweeping change to the way sport is structured, after its work found “the widespread presence of maltreatment and abuse” in a poorly resourced and organized system.",
      "bias_heuristic": {
        "article_type": "News",
        "sentiment": 0.0,
        "subjectivity_hint": "low"
      }
    },
    {
      "id": "80d0f518fe29d74a244a7f046e449412db69c7b5",
      "url": "https://www.cbc.ca/news/climate/record-heat-dome-9.7139906?cmp=rss",
      "title": "Record-breaking heat dome growing to cover nearly the entire U.S.",
      "published_at": "2026-03-24T06:56:57-04:00",
      "section": "Top Stories",
      "summary_auto": "A huge heat dome is spreading across the United States. After breaking March records in 14 states with temperatures as high as 44.4 C, it's now widening and may become the most expansive heat dome ever.",
      "bias_heuristic": {
        "article_type": "News",
        "sentiment": 0.7,
        "subjectivity_hint": "medium"
      }
    },
    {
      "id": "3b74b49ff7a250f4ded8080511ba9559c808d9db",
      "url": "https://www.cbc.ca/news/entertainment/celine-dion-posters-paris-9.7139862?cmp=rss",
      "title": "Mysterious posters hinting at Céline Dion's rumoured return pop up in Paris",
      "published_at": "2026-03-24T06:45:55-04:00",
      "section": "Top Stories",
      "summary_auto": "A social media post by Dion herself and the new posters across Paris are fueling speculation about the singer's reported return to performing. But representatives for the Quebec star have not confirmed any performances.",
      "bias_heuristic": {
        "article_type": "News",
        "sentiment": 0.0,
        "subjectivity_hint": "low"
      }
    },
    {
      "id": "60b67369e790a6b2cb697769b4f90d90744fcc1a",
      "url": "https://www.cbc.ca/news/investigates/iran-war-sleeper-cells-risk-intelligence-experts-9.7138536?cmp=rss",
      "title": "Are Iranian 'sleeper cells' a threat to Canadians? Here’s what intelligence experts say",
      "published_at": "2026-03-24T05:34:44-04:00",
      "section": "Top Stories",
      "summary_auto": "",
      "bias_heuristic": {
        "article_type": "News",
        "sentiment": -0.077,
        "subjectivity_hint": "low"
      }
    },
    {
      "id": "6e05febf9e70a18c37bc5c3bd7c324a0b76bf214",
      "url": "https://www.cbc.ca/news/canada/edmonton/emergency-doctors-pay-arrangement-alberta-9.7139373?cmp=rss",
      "title": "Edmonton emergency doctors and hospitalists warn of ER backlogs when stipend payments end",
      "published_at": "2026-03-24T04:00:00-04:00",
      "section": "Health",
      "summary_auto": "Some family doctors and emergency room physicians working in Edmonton hospitals warn that an April 1 end to stipend pay arrangements could put patient care at risk and increase suffering.",
      "bias_heuristic": {
        "article_type": "News",
        "sentiment": -0.727,
        "subjectivity_hint": "medium"
      }
    },
    {
      "id": "bec82d96a82a5ec03d070114cf9f326a64fe3d68",
      "url": "https://www.cbc.ca/news/canada/windsor/some-u-s-car-buyers-envy-what-they-cannot-have-affordable-chinese-evs-9.7139717?cmp=rss",
      "title": "Some U.S. car buyers envy what they cannot have — affordable Chinese EVs",
      "published_at": "2026-03-24T03:41:08-04:00",
      "section": "Business",
      "summary_auto": "Survey shows 40 per cent of U.S. consumers ​support Chinese auto imports, while political opposition in U.S. remains strong",
      "bias_heuristic": {
        "article_type": "News",
        "sentiment": 0.296,
        "subjectivity_hint": "low"
      }
    },
    {
      "id": "fcdbbe070e0614823c4f8a2bff5db2ba635a5925",
      "url": "https://www.cbc.ca/news/world/trump-administration-totalenergies-offshore-wind-9.7139677?cmp=rss",
      "title": "U.S. to pay French company $1B to scrap offshore wind projects",
      "published_at": "2026-03-24T03:12:58-04:00",
      "section": "World",
      "summary_auto": "The Trump administration will pay $1 billion to a France's TotalEnergies to walk away from two U.S. offshore wind leases as the administration ramps up its campaign against offshore wind and other renewable energy.",
      "bias_heuristic": {
        "article_type": "News",
        "sentiment": 0.077,
        "subjectivity_hint": "low"
      }
    },
    {
      "id": "40a088a943855891d3e8951b7f005a7bea03cd1b",
      "url": "https://www.cbc.ca/news/canada/newfoundland-labrador/weather-march-24-9.7139668?cmp=rss",
      "title": "St. John's metro schools stay closed, as winter storm slams parts of Newfoundland",
      "published_at": "2026-03-24T01:51:53-04:00",
      "section": "Canada",
      "summary_auto": "Much of Newfoundland is waking up to blustery and messy morning that will keep schools closed in the St. John's metro area and other parts of the island as another storm hits parts of N.L.",
      "bias_heuristic": {
        "article_type": "News",
        "sentiment": -0.361,
        "subjectivity_hint": "low"
      }
    },
    {
      "id": "d16349f1ef4d59493d7566f9efd59686e00cb211",
      "url": "https://www.cbc.ca/news/canada/nova-scotia/foster-care-group-homes-support-raising-age-limit-9.7138740?cmp=rss",
      "title": "N.S. bill aims to extend support for youth in foster care who age out of the system",
      "published_at": "2026-03-24T01:00:00-04:00",
      "section": "Canada",
      "summary_auto": "A bill before the Nova Scotia Legislature is proposing a change to the age when young people in the foster care or group home system can get provincial support, raising it from 19 to 26.",
      "bias_heuristic": {
        "article_type": "News",
        "sentiment": 0.91,
        "subjectivity_hint": "low"
      }
    },
    {
      "id": "77c8bbaa7997d3c9960f9e462129f1988f622c4f",
      "url": "https://www.cbc.ca/news/canada/nova-scotia/trout-kejimkujik-chain-pickerel-invasion-9.7136132?cmp=rss",
      "title": "Trout catch at Kejimkujik decimated by invasion of voracious predator",
      "published_at": "2026-03-24T01:00:00-04:00",
      "section": "Technology & Science",
      "summary_auto": "Kejimkujik National Park is pausing its annual brook trout census because an invasive species is devastating the local ecosystem.",
      "bias_heuristic": {
        "article_type": "News",
        "sentiment": -0.649,
        "subjectivity_hint": "low"
      }
    },
    {
      "id": "a0c881fd40ae7806162ed5ab3f4ec589f2b83a0e",
      "url": "https://www.cbc.ca/news/canada/newfoundland-labrador/st-johns-gull-cull-9.7138953?cmp=rss",
      "title": "St. John's airport has a seagull problem. But critics say more than a decade of culls hasn't made things safer",
      "published_at": "2026-03-24T00:30:00-04:00",
      "section": "Top Stories",
      "summary_auto": "The City of St. John's has killed thousands of gulls at the Robin Hood Bay landfill as part of its wildlife management plan, but some critics say the city is taking the wrong approach.",
      "bias_heuristic": {
        "article_type": "News",
        "sentiment": -0.968,
        "subjectivity_hint": "low"
      }
    },
    {
      "id": "c31f7dfbd556d4f97edc13b9f5d01444762fc923",
      "url": "https://www.cbc.ca/news/canada/newfoundland-labrador/moms-feel-the-burn-and-a-sense-of-community-while-their-babies-are-looked-after-9.7136614?cmp=rss",
      "title": "Moms feel the burn — and a sense of community — while their babies are looked after",
      "published_at": "2026-03-24T00:30:00-04:00",
      "section": "Health",
      "summary_auto": "The Islander Athletics \"mom club\" allows parents to work out while their kids are looked after, building muscle and community.",
      "bias_heuristic": {
        "article_type": "News",
        "sentiment": 0.0,
        "subjectivity_hint": "low"
      }
    },
    {
      "id": "f1859fcff6c103235cc964e2292a7539f42f1b0a",
      "url": "https://www.cbc.ca/news/indigenous/rcmp-spies-1970s-indigenous-rights-9.7134112?cmp=rss",
      "title": "How RCMP spies infiltrated the 1970s Indigenous rights movement",
      "published_at": "2026-03-24T00:00:21-04:00",
      "section": "Top Stories",
      "summary_auto": "",
      "bias_heuristic": {
        "article_type": "News",
        "sentiment": 0.0,
        "subjectivity_hint": "low"
      }
    },
    {
      "id": "24f948902fcf6184bc813be16308be38d2df546a",
      "url": "https://www.cbc.ca/news/canada/toronto/ontario-high-school-e-learning-9.7139226?cmp=rss",
      "title": "Ontario mandated e-learning to expand course options. Some worry it's being used to boost marks",
      "published_at": "2026-03-24T00:00:00-04:00",
      "section": "Top Stories",
      "summary_auto": "Six years after the Ontario government made e-learning a mandatory requirement for a high school diploma, students don't appear to be taking online school to diversify their course selection as the province had intended, according to a CBC News analysis of provincial enrolment data.",
      "bias_heuristic": {
        "article_type": "News",
        "sentiment": 0.34,
        "subjectivity_hint": "low"
      }
    },
    {
      "id": "7e9926ea35e7cd686995797dd5af32bc4c120c25",
      "url": "https://www.cbc.ca/news/world/syrian-refugees-return-from-lebanon-9.7135484?cmp=rss",
      "title": "Syrians fleeing Israeli strikes in Lebanon return home to a country still rebuilding",
      "published_at": "2026-03-24T00:00:00-04:00",
      "section": "Top Stories",
      "summary_auto": "More than 125,000 people have crossed from Lebanon into Syria this month, fleeing escalating violence and returning to a country that's still struggling to rebuild after more than a decade of civil war.",
      "bias_heuristic": {
        "article_type": "News",
        "sentiment": -0.923,
        "subjectivity_hint": "low"
      }
    },
    {
      "id": "6aa4c2a514781942745aba9c3ca6b347676d38fd",
      "url": "https://www.cbc.ca/news/canada/windsor/harlequin-romance-books-windsor-9.7136637?cmp=rss",
      "title": "2,000 happily ever afters: Ontario woman attempts to sell huge collection of Harlequin paperbacks",
      "published_at": "2026-03-24T00:00:00-04:00",
      "section": "Top Stories",
      "summary_auto": "Book collector Krystin Golden of Windsor says the Harlequin Intrigue line of novels isn't just about romance, and that's why she has spent decades accumulating titles. But now she'd like to sell all 2,000 of them as a single lot.",
      "bias_heuristic": {
        "article_type": "News",
        "sentiment": 0.641,
        "subjectivity_hint": "low"
      }
    },
    {
      "id": "513c5981962c1db02ca63c2246187bd33ca08eba",
      "url": "https://www.cbc.ca/news/canada/calgary/bakx-smith-ceraweek-foreign-investment-pipeline-9.7139057?cmp=rss",
      "title": "Smith-Carney pipeline deal to miss early deadlines, premier says",
      "published_at": "2026-03-24T00:00:00-04:00",
      "section": "Top Stories",
      "summary_auto": "The first set of deadlines included in the energy and climate deal struck between Prime Minister Mark Carney and Alberta Premier Danielle Smith are not expected to be met, showing early challenges with the agreement that includes pursuing a new export pipeline from Alberta to the West Coast.",
      "bias_heuristic": {
        "article_type": "News",
        "sentiment": 0.459,
        "subjectivity_hint": "low"
      }
    },
    {
      "id": "5b8472025e707df6fd5dfb566c18a9f6e9e28f68",
      "url": "https://www.cbc.ca/news/canada/thunder-bay/slfnha-medical-transportation-thunder-bay-9.7139118?cmp=rss",
      "title": "First Nation medical transportation program in Thunder Bay, Ont., axed over lack of funding",
      "published_at": "2026-03-24T00:00:00-04:00",
      "section": "Canada",
      "summary_auto": "The Sioux Lookout First Nations Health Authority (SLFNHA) has announced it is suspending its medical transportation program in Thunder Bay, Ont., due to a lack of funding from Indigenous Services Canada and the Non-Insured Health Benefits program. Here's what the change means for people who rely on the service and the more than 20 staff members who have been laid off.",
      "bias_heuristic": {
        "article_type": "News",
        "sentiment": -0.459,
        "subjectivity_hint": "low"
      }
    },
    {
      "id": "11695fa39b9eace68aac6ffa8e9d9fcc08458fcf",
      "url": "https://www.cbc.ca/news/editorsblog/cbc-news-indigenous-rcmp-surveillance-9.7133525?cmp=rss",
      "title": "How the RCMP spied on Indigenous organizations — and how we broke the story",
      "published_at": "2026-03-24T00:00:00-04:00",
      "section": "Canada",
      "summary_auto": "Today, we begin publishing a series of exclusive stories that expose a sweeping RCMP program of surveillance, disruption and infiltration of Indigenous organizations between 1968 and 1982. Though long suspected by Indigenous leaders across Canada, the scope and scale of the spy program has remained hidden behind walls of government secrecy, until now.",
      "bias_heuristic": {
        "article_type": "News",
        "sentiment": -0.743,
        "subjectivity_hint": "medium"
      }
    },
    {
      "id": "17b9394177d37243bd40360c938a8128b39b204d",
      "url": "https://www.cbc.ca/news/world/markwayne-mullin-dhs-approved-9.7139568?cmp=rss",
      "title": "U.S. Senate approves Markwayne Mullin as next head of Homeland Security",
      "published_at": "2026-03-23T17:44:01-04:00",
      "section": "World",
      "summary_auto": "The U.S. Senate confirmed Markwayne Mullin as homeland security secretary late Monday, approving President Donald Trump's nominee to take over the embattled department after the firing of Kristi Noem.",
      "bias_heuristic": {
        "article_type": "News",
        "sentiment": 0.625,
        "subjectivity_hint": "low"
      }
    },
    {
      "id": "ed6a303e3b20862fc520f265e5490346b1ab400b",
      "url": "https://www.cbc.ca/news/canada/british-columbia/tesla-driver-sleeping-rainy-rush-hour-9.7139522?cmp=rss",
      "title": "Tesla driver caught asleep at wheel during rainy rush hour: RCMP",
      "published_at": "2026-03-23T17:04:57-04:00",
      "section": "Canada",
      "summary_auto": "Police in Metro Vancouver are warning drivers to remain attentive, even in a self-driving vehicle, after ticketing a woman who \"appeared to be literally asleep at the wheel\" on Highway 1.",
      "bias_heuristic": {
        "article_type": "News",
        "sentiment": -0.402,
        "subjectivity_hint": "low"
      }
    },
    {
      "id": "a0cc5598b46ab7b1f9aaf6019538300254a0ed14",
      "url": "https://www.cbc.ca/news/canada/nova-scotia/n-s-judge-to-rule-on-2015-air-canada-crash-landing-class-action-settlement-9.7139483?cmp=rss",
      "title": "N.S. judge to rule on proposed $18M settlement in 2015 Air Canada Halifax crash landing",
      "published_at": "2026-03-23T16:22:48-04:00",
      "section": "Canada",
      "summary_auto": "The class action was filed in 2015 and scheduled for trial earlier this year, but a notice released Monday said the proposed settlement could avoid a lengthy court process and probably offer larger compensation.",
      "bias_heuristic": {
        "article_type": "News",
        "sentiment": -0.565,
        "subjectivity_hint": "medium"
      }
    },
    {
      "id": "714d5cc6f9df3b5267639b95dd98111a27ed31a1",
      "url": "https://www.cbc.ca/news/entertainment/bill-cosby-guilty-sexual-assault-9.7139436?cmp=rss",
      "title": "Jury finds Bill Cosby sexually assaulted woman in 1972, awards her nearly $60M US",
      "published_at": "2026-03-23T15:51:52-04:00",
      "section": "World",
      "summary_auto": "A civil jury in California found that Bill Cosby was liable for drugging and sexually assaulting a woman in 1972 and awarded her $59.25 million US on Monday.",
      "bias_heuristic": {
        "article_type": "News",
        "sentiment": -0.25,
        "subjectivity_hint": "medium"
      }
    },
    {
      "id": "0f728427303d4deb819d5c3bb20e820d72045f16",
      "url": "https://www.cbc.ca/player/play/9.7139424?cmp=rss",
      "title": "The moment a plane smashed into a fire truck at LaGuardia Airport | About That",
      "published_at": "2026-03-23T15:39:56-04:00",
      "section": "World",
      "summary_auto": "Air Canada Flight 8646 collided with a fire truck at New York's LaGuardia Airport, killing two pilots and injuring dozens of others. Andrew Chang breaks down what we know about the crash from air traffic control audio and insight from aviation experts. Images provided by The Canadian Press, Reuters and Getty Images",
      "bias_heuristic": {
        "article_type": "News",
        "sentiment": -0.898,
        "subjectivity_hint": "medium"
      }
    },
    {
      "id": "4174fb2921902c957eb4a25ea80c5b1b273729c8",
      "url": "https://www.cbc.ca/news/canada/manitoba/measles-spring-break-school-divisions-9.7139029?cmp=rss",
      "title": "Consider measles risks in spring break vacation plans, health officials urge Manitoba parents",
      "published_at": "2026-03-23T15:22:16-04:00",
      "section": "Health",
      "summary_auto": "Manitoba parents and guardians received a warning from public health officials ahead of spring break vacations and Easter holidays asking them to consider measles risks while travelling or attending large gatherings.",
      "bias_heuristic": {
        "article_type": "News",
        "sentiment": -0.459,
        "subjectivity_hint": "low"
      }
    }
  ]
}